teneva/__init__.py
teneva/act_many.py
teneva/act_one.py
teneva/act_two.py
teneva/als.py
teneva/als_func.py
teneva/anova.py
teneva/anova_func.py
teneva/core.py
teneva/cross.py
teneva/cross_act.py
teneva/data.py
teneva/func.py
teneva/func_full.py
teneva/grid.py
teneva/matrices.py
teneva/maxvol.py
teneva/optima.py
teneva/optima_func.py
teneva/props.py
teneva/sample.py
teneva/sample_func.py
teneva/stat.py
teneva/svd.py
teneva/tensors.py
teneva/transformation.py
teneva/utils.py
teneva/vectors.py
teneva/vis.py
teneva-0.14.9.dist-info/LICENSE.txt
teneva-0.14.9.dist-info/METADATA
teneva-0.14.9.dist-info/WHEEL
teneva-0.14.9.dist-info/top_level.txt
teneva-0.14.9.dist-info/RECORD
