Metadata-Version: 2.1
Name: teneva
Version: 0.14.9
Summary: Compact implementation of basic operations in the tensor-train (TT) format, including TT-SVD, TT-ALS, TT-ANOVA, TT-CROSS, TT-truncate for approximation of multidimensional arrays and multivariate functions
Home-page: https://github.com/AndreiChertkov/teneva
Author: Andrei Chertkov
Author-email: andre.chertkov@gmail.com
License: MIT
Project-URL: Source, https://github.com/AndreiChertkov/teneva
Keywords: low-rank representation tensor train format TT-decomposition cross approximation als anova
Classifier: Development Status :: 4 - Beta
Classifier: License :: OSI Approved :: MIT License
Classifier: Topic :: Scientific/Engineering
Classifier: Topic :: Scientific/Engineering :: Mathematics
Classifier: Topic :: Scientific/Engineering :: Information Analysis
Classifier: Topic :: Scientific/Engineering :: Artificial Intelligence
Classifier: Intended Audience :: Science/Research
Classifier: Operating System :: OS Independent
Classifier: Programming Language :: Python :: 3
Classifier: Programming Language :: Python :: 3 :: Only
Classifier: Programming Language :: Python :: 3.8
Classifier: Programming Language :: Python :: 3.9
Classifier: Framework :: Jupyter
Requires-Python: >=3.8
License-File: LICENSE.txt
Requires-Dist: opt-einsum >=3.3
Requires-Dist: numpy <1.22 ; python_version == "3.7"
Requires-Dist: scipy <1.8 ; python_version == "3.7"
Requires-Dist: numpy <1.25,>=1.22 ; python_version == "3.8"
Requires-Dist: scipy <1.11,>=1.9 ; python_version == "3.8"
Requires-Dist: numpy >=1.22 ; python_version >= "3.9"
Requires-Dist: scipy >=1.9 ; python_version >= "3.9"
